prefect/.prefectignore
prefect/AGENTS.md
prefect/__init__.py
prefect/__main__.py
prefect/_build_info.py
prefect/_observers.py
prefect/_result_records.py
prefect/_states.py
prefect/_versioning.py
prefect/_waiters.py
prefect/agent.py
prefect/artifacts.py
prefect/automations.py
prefect/cache_policies.py
prefect/context.py
prefect/engine.py
prefect/exceptions.py
prefect/filesystems.py
prefect/flow_engine.py
prefect/flow_runs.py
prefect/flows.py
prefect/futures.py
prefect/main.py
prefect/plugins.py
prefect/py.typed
prefect/results.py
prefect/schedules.py
prefect/serializers.py
prefect/states.py
prefect/task_engine.py
prefect/task_runners.py
prefect/task_runs.py
prefect/task_worker.py
prefect/tasks.py
prefect/transactions.py
prefect/variables.py
prefect/_experimental/__init__.py
prefect/_experimental/bundles/__init__.py
prefect/_experimental/bundles/execute.py
prefect/_experimental/plugins/__init__.py
prefect/_experimental/plugins/apply.py
prefect/_experimental/plugins/diagnostics.py
prefect/_experimental/plugins/manager.py
prefect/_experimental/plugins/spec.py
prefect/_experimental/sla/__init__.py
prefect/_experimental/sla/client.py
prefect/_experimental/sla/objects.py
prefect/_internal/__init__.py
prefect/_internal/_logging.py
prefect/_internal/installation.py
prefect/_internal/integrations.py
prefect/_internal/lazy.py
prefect/_internal/observability.py
prefect/_internal/pytz.py
prefect/_internal/retries.py
prefect/_internal/send_entrypoint_logs.py
prefect/_internal/testing.py
prefect/_internal/urls.py
prefect/_internal/uuid7.py
prefect/_internal/websockets.py
prefect/_internal/compatibility/__init__.py
prefect/_internal/compatibility/async_dispatch.py
prefect/_internal/compatibility/backports.py
prefect/_internal/compatibility/blocks.py
prefect/_internal/compatibility/deprecated.py
prefect/_internal/compatibility/migration.py
prefect/_internal/compatibility/starlette.py
prefect/_internal/concurrency/__init__.py
prefect/_internal/concurrency/api.py
prefect-3.6.14.dist-info/METADATA
prefect-3.6.14.dist-info/WHEEL
prefect-3.6.14.dist-info/entry_points.txt
prefect-3.6.14.dist-info/licenses/LICENSE
prefect-3.6.14.dist-info/RECORD
